TensorflowJiaochengHvass/README.md
TensorflowJiaochengHvass/__init__.py
TensorflowJiaochengHvass/__main__.py
TensorflowJiaochengHvass/file.epub
TensorflowJiaochengHvass/index.html
TensorflowJiaochengHvass/css/__init__.py
TensorflowJiaochengHvass/css/annotations.css
TensorflowJiaochengHvass/css/main.css
TensorflowJiaochengHvass/css/normalize.css
TensorflowJiaochengHvass/css/popup.css
TensorflowJiaochengHvass/font/__init__.py
TensorflowJiaochengHvass/font/fontello.eot
TensorflowJiaochengHvass/font/fontello.svg
TensorflowJiaochengHvass/font/fontello.ttf
TensorflowJiaochengHvass/font/fontello.woff
TensorflowJiaochengHvass/img/__init__.py
TensorflowJiaochengHvass/img/annotator-glyph-sprite.png
TensorflowJiaochengHvass/img/annotator-icon-sprite.png
TensorflowJiaochengHvass/img/apple-touch-icon.png
TensorflowJiaochengHvass/img/cancelfullscreen.png
TensorflowJiaochengHvass/img/close.png
TensorflowJiaochengHvass/img/fullscreen.png
TensorflowJiaochengHvass/img/loader.gif
TensorflowJiaochengHvass/img/menu-icon.png
TensorflowJiaochengHvass/img/save.png
TensorflowJiaochengHvass/img/saved.png
TensorflowJiaochengHvass/img/settings-s.png
TensorflowJiaochengHvass/img/settings.png
TensorflowJiaochengHvass/img/star.png
TensorflowJiaochengHvass/js/__init__.py
TensorflowJiaochengHvass/js/epub.js
TensorflowJiaochengHvass/js/epub.min.js
TensorflowJiaochengHvass/js/epub.min.map
TensorflowJiaochengHvass/js/hooks.min.js
TensorflowJiaochengHvass/js/hooks.min.map
TensorflowJiaochengHvass/js/reader.js
TensorflowJiaochengHvass/js/reader.js.map
TensorflowJiaochengHvass/js/reader.min.js
TensorflowJiaochengHvass/js/reader.min.map
TensorflowJiaochengHvass/js/hooks/__init__.py
TensorflowJiaochengHvass/js/hooks/extensions/__init__.py
TensorflowJiaochengHvass/js/hooks/extensions/highlight.js
TensorflowJiaochengHvass/js/libs/__init__.py
TensorflowJiaochengHvass/js/libs/jquery.min.js
TensorflowJiaochengHvass/js/libs/localforage.min.js
TensorflowJiaochengHvass/js/libs/screenfull.js
tensorflow_jiaocheng_hvass-2024.3.2.0.dist-info/METADATA
tensorflow_jiaocheng_hvass-2024.3.2.0.dist-info/WHEEL
tensorflow_jiaocheng_hvass-2024.3.2.0.dist-info/entry_points.txt
tensorflow_jiaocheng_hvass-2024.3.2.0.dist-info/top_level.txt
tensorflow_jiaocheng_hvass-2024.3.2.0.dist-info/RECORD
